chapa_cli/__init__.py
chapa_cli/main.py
chapa_cli/transaction.py
chapa_cli/utils.py
chapa_cli/webhook.py
tests/__init__.py
tests/test_transaction.py
tests/test_webhook.py
chapa_cli-0.0.4.dist-info/LICENSE
chapa_cli-0.0.4.dist-info/METADATA
chapa_cli-0.0.4.dist-info/WHEEL
chapa_cli-0.0.4.dist-info/entry_points.txt
chapa_cli-0.0.4.dist-info/top_level.txt
chapa_cli-0.0.4.dist-info/RECORD
