Metadata-Version: 2.1
Name: chapa-cli
Version: 0.0.4
Summary: A CLI tool for integrating with Chapa API.
Home-page: https://github.com/Chapa-Et/chapa-cli
Author: Israel Goytom
Author-email: israel@chapa.co
Classifier: Programming Language :: Python :: 3
Classifier: License :: OSI Approved :: MIT License
Classifier: Operating System :: OS Independent
Requires-Python: >=3.7
License-File: LICENSE
Requires-Dist: requests
Requires-Dist: click
Requires-Dist: flask
Requires-Dist: pyngrok
Requires-Dist: rich
